finance_byu/LICENSE.txt
finance_byu/__init__.py
finance_byu/fama_macbeth.py
finance_byu/regression.py
finance_byu/regtables.py
finance_byu/rolling.py
finance_byu/statistics.py
finance_byu/summarize.py
finance_byu-0.2.0.dist-info/METADATA
finance_byu-0.2.0.dist-info/WHEEL
finance_byu-0.2.0.dist-info/top_level.txt
finance_byu-0.2.0.dist-info/RECORD
