Metadata-Version: 2.1
Name: finance-byu
Version: 0.2.0
Summary: Classes and functions for FIN 585 and finance research at Brigham Young University
Author: Damon Petersen
Author-email: Damon Petersen <damon.petersen@chicagobooth.edu>
License: MIT
Project-URL: Homepage, https://fin-library.readthedocs.io/en/latest/
Classifier: Programming Language :: Python :: 3
Classifier: License :: OSI Approved :: MIT License
Classifier: Operating System :: OS Independent
Requires-Python: >=3.6
Requires-Dist: numpy
Requires-Dist: pandas
Requires-Dist: joblib
Requires-Dist: statsmodels
Requires-Dist: numba
Requires-Dist: scipy
Requires-Dist: patsy
